{
    "name": "scene",
    "objects": [
        {
            "type": "LIGHT",
            "name": "Light",
            "transform": {
                "translation": [
                    4.076245307922363,
                    1.0054539442062378,
                    5.903861999511719
                ],
                "rotation": [
                    37.26104736328125,
                    3.1637091636657715,
                    106.93632507324219
                ],
                "scaling": [
                    1.0,
                    0.9999999403953552,
                    1.0
                ]
            }
        },
        {
            "type": "CAMERA",
            "name": "Camera",
            "transform": {
                "translation": [
                    7.358891487121582,
                    -6.825790882110596,
                    5.198308944702148
                ],
                "rotation": [
                    62.359291076660156,
                    -1.4407337403099518e-06,
                    46.69194412231445
                ],
                "scaling": [
                    1.0,
                    1.0,
                    1.0
                ]
            },
            "camera_type": "Perspective",
            "fov": 0.34557520356786753,
            "aspect_ratio": 1.7777777777777777,
            "far_clip": 1000.0,
            "near_clip": 0.10000000149011612
        },
        {
            "type": "MESH",
            "name": "Cube",
            "transform": {
                "translation": [
                    0.0,
                    0.0,
                    0.0
                ],
                "rotation": [
                    0.0,
                    -0.0,
                    0.0
                ],
                "scaling": [
                    1.0,
                    1.0,
                    1.0
                ]
            },
            "file_name": "./Resources/Common/Cube.obj"
        }
    ]
}