{
    "name": "scene",
    "objects": [
        {
            "type": "MESH",
            "name": "Cube",
            "transform": {
                "translation": [
                    0.0,
                    0.0,
                    2.7097723484039307
                ],
                "rotation": [
                    -63.23102951049805,
                    2.889869451522827,
                    72.34786224365234
                ],
                "scaling": [
                    0.9999999403953552,
                    1.0,
                    2.4985122680664062
                ]
            },
            "file_name": "./Resources/Common/Cube.obj"
        },
        {
            "type": "LIGHT",
            "name": "Light",
            "transform": {
                "translation": [
                    4.076245307922363,
                    1.0054539442062378,
                    5.903861999511719
                ],
                "rotation": [
                    37.26104736328125,
                    3.1637091636657715,
                    106.93632507324219
                ],
                "scaling": [
                    1.0,
                    0.9999999403953552,
                    1.0
                ]
            }
        },
        {
            "type": "CAMERA",
            "name": "Camera",
            "transform": {
                "translation": [
                    -39.09486389160156,
                    -54.82406234741211,
                    10.09627914428711
                ],
                "rotation": [
                    89.95936584472656,
                    2.9006290787947364e-05,
                    -25.7081356048584
                ],
                "scaling": [
                    1.0,
                    1.0,
                    1.0
                ]
            },
            "camera_type": "Perspective",
            "fov": 0.4816912699247473,
            "aspect_ratio": 1.7777777777777777,
            "far_clip": 1000.0,
            "near_clip": 0.10000000149011612
        },
        {
            "type": "MESH",
            "name": "Cube.001",
            "transform": {
                "translation": [
                    -26.757749557495117,
                    0.5180812478065491,
                    9.129142761230469
                ],
                "rotation": [
                    -46.091041564941406,
                    -6.458860397338867,
                    -67.37822723388672
                ],
                "scaling": [
                    1.0,
                    0.9999999403953552,
                    2.4985122680664062
                ]
            },
            "file_name": "./Resources/Common/Cube.obj"
        },
        {
            "type": "MESH",
            "name": "Cube.002",
            "transform": {
                "translation": [
                    -6.196130752563477,
                    -9.377981185913086,
                    13.005077362060547
                ],
                "rotation": [
                    -58.65806579589844,
                    -35.40549087524414,
                    169.00830078125
                ],
                "scaling": [
                    1.0,
                    1.0,
                    2.4985125064849854
                ]
            },
            "file_name": "./Resources/Common/Cube.obj"
        }
    ]
}